unreal/__init__.py
unreal/unreal.py
unreal_stub-0.3.dist-info/METADATA
unreal_stub-0.3.dist-info/WHEEL
unreal_stub-0.3.dist-info/top_level.txt
unreal_stub-0.3.dist-info/RECORD
