Metadata-Version: 2.4
Name: unreal_stub
Version: 0.3
Summary: Python stub for Unreal Engine 5 API - latest: 5.6.0
Dynamic: description
Dynamic: description-content-type
Dynamic: summary
